posta/__init__.py
posta/send_message.py
posta-0.1.1.dist-info/WHEEL
posta-0.1.1.dist-info/METADATA
posta-0.1.1.dist-info/RECORD
